color_debugger.py
color_debugger-1.0.1.dist-info/WHEEL
color_debugger-1.0.1.dist-info/METADATA
color_debugger-1.0.1.dist-info/RECORD
